study_lyte/__init__.py
study_lyte/adjustments.py
study_lyte/cropping.py
study_lyte/decorators.py
study_lyte/depth.py
study_lyte/detect.py
study_lyte/io.py
study_lyte/logging.py
study_lyte/plotting.py
study_lyte/profile.py
study_lyte/relationships.py
study_lyte/stats.py
study_lyte/styles.py
study_lyte-0.7.0.dist-info/LICENSE
study_lyte-0.7.0.dist-info/METADATA
study_lyte-0.7.0.dist-info/WHEEL
study_lyte-0.7.0.dist-info/top_level.txt
study_lyte-0.7.0.dist-info/RECORD
