Metadata-Version: 2.1
Name: study-lyte
Version: 0.7.0
Summary: Package for doing analysis with Lyte Probe data
Home-page: https://github.com/AdventureData/study_lyte
Author: Micah Johnson 
Author-email: info@adventuredata.com
License: GNU General Public License v3
Keywords: study_lyte
Classifier: Development Status :: 2 - Pre-Alpha
Classifier: Intended Audience :: Developers
Classifier: License :: OSI Approved :: GNU General Public License v3 (GPLv3)
Classifier: Natural Language :: English
Classifier: Programming Language :: Python :: 3
Classifier: Programming Language :: Python :: 3.6
Classifier: Programming Language :: Python :: 3.7
Classifier: Programming Language :: Python :: 3.8
Classifier: Programming Language :: Python :: 3.9
Classifier: Programming Language :: Python :: 3.10
Requires-Python: >=3.6
License-File: LICENSE
Requires-Dist: pandas >1.2.0
Requires-Dist: pandas <2.0.0
Requires-Dist: scipy >=1.8.0
Requires-Dist: scipy <2.0.0
Requires-Dist: shapely
